parc_checker_api/parc_checker_api.py
parc_checker_api-1.5.dist-info/METADATA
parc_checker_api-1.5.dist-info/WHEEL
parc_checker_api-1.5.dist-info/top_level.txt
parc_checker_api-1.5.dist-info/RECORD
