Metadata-Version: 2.1
Name: parc-checker-api
Version: 1.5
Summary: API library for PARC Checker
Home-page: UNKNOWN
Author: Dovydas Jančauskas
Author-email: dovydasjan@gmail.com
License: UNKNOWN
Platform: UNKNOWN
Requires-Dist: flask
Requires-Dist: flask-cors
Requires-Dist: parc-checker-core (==1.2)
Provides-Extra: dev
Requires-Dist: pytest ; extra == 'dev'
Requires-Dist: pytest-cov ; extra == 'dev'
Requires-Dist: wheel ; extra == 'dev'
